odoo/addons/account_invoice_refund_reason/README.rst
odoo/addons/account_invoice_refund_reason/__init__.py
odoo/addons/account_invoice_refund_reason/__manifest__.py
odoo/addons/account_invoice_refund_reason/data/account.invoice.refund.reason.csv
odoo/addons/account_invoice_refund_reason/i18n/account_invoice_refund_reason.pot
odoo/addons/account_invoice_refund_reason/i18n/es.po
odoo/addons/account_invoice_refund_reason/i18n/hr.po
odoo/addons/account_invoice_refund_reason/models/__init__.py
odoo/addons/account_invoice_refund_reason/models/account_invoice.py
odoo/addons/account_invoice_refund_reason/models/account_invoice_refund_reason.py
odoo/addons/account_invoice_refund_reason/readme/CONFIGURE.rst
odoo/addons/account_invoice_refund_reason/readme/CONTRIBUTORS.rst
odoo/addons/account_invoice_refund_reason/readme/DESCRIPTION.rst
odoo/addons/account_invoice_refund_reason/readme/USAGE.rst
odoo/addons/account_invoice_refund_reason/security/ir.model.access.csv
odoo/addons/account_invoice_refund_reason/static/description/icon.png
odoo/addons/account_invoice_refund_reason/static/description/index.html
odoo/addons/account_invoice_refund_reason/tests/__init__.py
odoo/addons/account_invoice_refund_reason/tests/test_account_invoice_refund_reason.py
odoo/addons/account_invoice_refund_reason/views/account_invoice_refund_reason_view.xml
odoo/addons/account_invoice_refund_reason/views/account_invoice_view.xml
odoo/addons/account_invoice_refund_reason/wizard/__init__.py
odoo/addons/account_invoice_refund_reason/wizard/account_invoice_refund.py
odoo/addons/account_invoice_refund_reason/wizard/account_invoice_refund_view.xml
odoo12_addon_account_invoice_refund_reason-12.0.1.0.1.dist-info/METADATA
odoo12_addon_account_invoice_refund_reason-12.0.1.0.1.dist-info/WHEEL
odoo12_addon_account_invoice_refund_reason-12.0.1.0.1.dist-info/top_level.txt
odoo12_addon_account_invoice_refund_reason-12.0.1.0.1.dist-info/RECORD
